goreverselookup/Model.py
goreverselookup/Workflows.py
goreverselookup/__init__.py
goreverselookup/config/__init__.py
goreverselookup/config/logging_config.json
goreverselookup/core/GOTerm.py
goreverselookup/core/Metrics.py
goreverselookup/core/ModelSettings.py
goreverselookup/core/ModelStats.py
goreverselookup/core/Product.py
goreverselookup/core/Report.py
goreverselookup/core/__init__.py
goreverselookup/core/miRNA.py
goreverselookup/log_output/__init__.py
goreverselookup/main_cli.py
goreverselookup/main_cli_installer.py
goreverselookup/main_gui.py
goreverselookup/main_gui2.py
goreverselookup/parse/GOAFParser.py
goreverselookup/parse/OBOParser.py
goreverselookup/parse/OrthologParsers.py
goreverselookup/parse/__init__.py
goreverselookup/util/ApiUtil.py
goreverselookup/util/CacheUtil.py
goreverselookup/util/DictUtil.py
goreverselookup/util/FileUtil.py
goreverselookup/util/JsonUtil.py
goreverselookup/util/LogConfigLoader.py
goreverselookup/util/Timer.py
goreverselookup/util/WebsiteParser.py
goreverselookup/util/__init__.py
goreverselookup/web_apis/EnsemblApi.py
goreverselookup/web_apis/GOApi.py
goreverselookup/web_apis/UniprotApi.py
goreverselookup/web_apis/__init__.py
goreverselookup/web_apis/gProfilerApi.py
goreverselookup-1.0.76.dist-info/METADATA
goreverselookup-1.0.76.dist-info/WHEEL
goreverselookup-1.0.76.dist-info/entry_points.txt
goreverselookup-1.0.76.dist-info/licenses/LICENSE
goreverselookup-1.0.76.dist-info/RECORD
