Metadata-Version: 2.4
Name: goreverselookup
Version: 1.0.76
Summary: Python library for Gene Ontology Reverse Lookup
License: Apache-2.0
License-File: LICENSE
Keywords: gene ontology,reverse lookup
Author: Aljoša Škorjanc
Author-email: skorjanc.aljosa@gmail.com
Requires-Python: >=3.10
Classifier: Development Status :: 3 - Alpha
Classifier: Intended Audience :: Science/Research
Classifier: License :: OSI Approved :: GNU General Public License v3 or later (GPLv3+)
Classifier: Programming Language :: Python :: 3
Classifier: Topic :: Scientific/Engineering :: Bio-Informatics
Provides-Extra: dev
Requires-Dist: aiohttp
Requires-Dist: asyncio
Requires-Dist: beautifulsoup4
Requires-Dist: black ; extra == "dev"
Requires-Dist: check-manifest ; extra == "dev"
Requires-Dist: mypy ; extra == "dev"
Requires-Dist: networkx
Requires-Dist: numpy
Requires-Dist: openpyxl
Requires-Dist: pandas
Requires-Dist: pytest ; extra == "dev"
Requires-Dist: pytest-asyncio ; extra == "dev"
Requires-Dist: requests
Requires-Dist: ruff ; extra == "dev"
Requires-Dist: scipy
Requires-Dist: statsmodels
Requires-Dist: tabulate
Requires-Dist: tox ; extra == "dev"
Requires-Dist: tqdm
